cvtron/__init__.py
cvtron/Base/Model.py
cvtron/Base/Task.py
cvtron/Base/Trainer.py
cvtron/Base/__init__.py
cvtron/Base/decorator.py
cvtron/data_zoo/__init__.py
cvtron/data_zoo/celeba_loader.py
cvtron/data_zoo/cifar_loader.py
cvtron/data_zoo/cyclegan_loader.py
cvtron/data_zoo/flicker_loader.py
cvtron/data_zoo/imagenet_classes.py
cvtron/data_zoo/imagenet_mean.py
cvtron/data_zoo/mnist_loader.py
cvtron/data_zoo/voc_loader.py
cvtron/data_zoo/hico/__init__.py
cvtron/data_zoo/hico/hico.py
cvtron/data_zoo/hico/hico_to_tfrecords.py
cvtron/data_zoo/hico/preprocess_hico_labels.py
cvtron/data_zoo/segment/SBD.py
cvtron/data_zoo/segment/__init__.py
cvtron/data_zoo/vlabel/__init__.py
cvtron/data_zoo/vlabel/parser.py
cvtron/functions/__init__.py
cvtron/functions/softmax.py
cvtron/model_zoo/__init__.py
cvtron/model_zoo/constant.py
cvtron/model_zoo/inception.py
cvtron/model_zoo/vgg_19.py
cvtron/model_zoo/deeplab/__init__.py
cvtron/model_zoo/deeplab/constant.py
cvtron/model_zoo/deeplab/deeplabV3.py
cvtron/model_zoo/icnet/__init__.py
cvtron/model_zoo/icnet/icnet.py
cvtron/model_zoo/inception/__init__.py
cvtron/model_zoo/inception/inceptionV3.py
cvtron/model_zoo/lapsrn/__init__.py
cvtron/model_zoo/lapsrn/config.py
cvtron/model_zoo/lapsrn/lapsrn.py
cvtron/model_zoo/resnet/__init__.py
cvtron/model_zoo/resnet/resnet_utils.py
cvtron/model_zoo/resnet/resnet_v2.py
cvtron/model_zoo/vgg/__init__.py
cvtron/model_zoo/vgg/constant.py
cvtron/model_zoo/vgg/vgg_19.py
cvtron/model_zoo/yolo/__init__.py
cvtron/model_zoo/yolo/net.py
cvtron/model_zoo/yolo/yolo_net.py
cvtron/model_zoo/yolo/yolo_tiny_net.py
cvtron/modeling/__init__.py
cvtron/modeling/classifier/__init__.py
cvtron/modeling/classifier/api.py
cvtron/modeling/classifier/image_classifier.py
cvtron/modeling/detector/__init__.py
cvtron/modeling/detector/api.py
cvtron/modeling/detector/object_detector.py
cvtron/modeling/segmentor/ImageSegmentor.py
cvtron/modeling/segmentor/__init__.py
cvtron-0.0.2.dist-info/DESCRIPTION.rst
cvtron-0.0.2.dist-info/METADATA
cvtron-0.0.2.dist-info/RECORD
cvtron-0.0.2.dist-info/WHEEL
cvtron-0.0.2.dist-info/metadata.json
cvtron-0.0.2.dist-info/top_level.txt
