Metadata-Version: 2.0
Name: cvtron
Version: 0.0.2
Summary: Out-of-the-Box Computer Vision Library
Home-page: https://github.com/cv-group
Author: Xiaozhe Yao
Author-email: ad@askfermi.me
License: MIT
Keywords: Computer Vision
Platform: UNKNOWN
Classifier: Development Status :: 5 - Production/Stable
Classifier: Intended Audience :: Developers
Classifier: Programming Language :: Python :: 3
Classifier: Programming Language :: Python :: 3.5
Classifier: Programming Language :: Python :: 3.6
Requires-Dist: tensorflow
Requires-Dist: tensorlayer
Requires-Dist: tqdm
Requires-Dist: requests
